autochat_lp-1.1.1.dist-info/DESCRIPTION.rst
autochat_lp-1.1.1.dist-info/METADATA
autochat_lp-1.1.1.dist-info/RECORD
autochat_lp-1.1.1.dist-info/WHEEL
autochat_lp-1.1.1.dist-info/metadata.json
autochat_lp-1.1.1.dist-info/top_level.txt
com/primo/autochat/AutoReply.py
com/primo/autochat/FriendStatus.py
com/primo/autochat/QunFa.py
com/primo/autochat/__init__.py
com/primo/autochat/gatherMsg.py
com/primo/autochat/qunNeiqunFa.py
com/primo/autochat/testSay.py
com/primo/autochat/testTuringApi.py
com/primo/autochat/turingApi.py
