Metadata-Version: 2.0
Name: autochat-lp
Version: 1.1.1
Summary: A auto reply project using itchat.
Home-page: https://github.com/calvinjiang/hive-executor-py
Author: Primo Lin
Author-email: 857912753@qq.com
License: MIT
Keywords: autoReply python
Platform: UNKNOWN
Classifier: Development Status :: 4 - Beta
Classifier: Intended Audience :: Developers
Classifier: Topic :: Software Development :: Build Tools
Classifier: License :: OSI Approved :: MIT License
Classifier: Programming Language :: Python :: 3.5
Classifier: Programming Language :: Python :: 3.6
Classifier: Programming Language :: Python :: 3.7
